MANIFEST.in
README.rst
setup.py
cssocialprofile/__init__.py
cssocialprofile/admin.py
cssocialprofile/forms.py
cssocialprofile/models.py
cssocialprofile/notes.txt
cssocialprofile/urls.py
cssocialprofile/views.py
cssocialprofile.egg-info/PKG-INFO
cssocialprofile.egg-info/SOURCES.txt
cssocialprofile.egg-info/dependency_links.txt
cssocialprofile.egg-info/entry_points.txt
cssocialprofile.egg-info/not-zip-safe
cssocialprofile.egg-info/requires.txt
cssocialprofile.egg-info/top_level.txt
cssocialprofile/locale/es/LC_MESSAGES/django.po
cssocialprofile/locale/eu/LC_MESSAGES/django.po
cssocialprofile/migrations/0001_initial.py
cssocialprofile/migrations/__init__.py
cssocialprofile/pipeline/__init__.py
cssocialprofile/pipeline/extra_values.py
cssocialprofile/templates/cssocialprofile/base.html
cssocialprofile/templates/cssocialprofile/header_useroptions.html
cssocialprofile/templates/profile/base.html
cssocialprofile/templates/profile/edit_personal.html
cssocialprofile/templates/profile/edit_photo.html
cssocialprofile/templates/profile/edit_social.html
cssocialprofile/templates/registration/activate.html
cssocialprofile/templates/registration/activation_complete.html
cssocialprofile/templates/registration/activation_email.txt
cssocialprofile/templates/registration/activation_email_subject.txt
cssocialprofile/templates/registration/base.html
cssocialprofile/templates/registration/login.html
cssocialprofile/templates/registration/password_reset.html
cssocialprofile/templates/registration/password_reset_complete.html
cssocialprofile/templates/registration/password_reset_confirm.html
cssocialprofile/templates/registration/password_reset_done.html
cssocialprofile/templates/registration/password_reset_email.txt
cssocialprofile/templates/registration/password_reset_form.html
cssocialprofile/templates/registration/registration_complete.html
cssocialprofile/templates/registration/registration_form.html
cssocialprofile/utils/__init__.py
cssocialprofile/utils/load_images.py
cssocialprofile/utils/slug.py