Metadata-Version: 1.0
Name: cssocialprofile
Version: 4.2
Summary: SocialProfile app extension
Home-page: http://www.codesyntax.com
Author: Josu Azpillaga
Author-email: jazpillaga@codesyntax.com
License: GPL
Platform: UNKNOWN
